log2c.py
setup.py
log2c.egg-info/PKG-INFO
log2c.egg-info/SOURCES.txt
log2c.egg-info/dependency_links.txt
log2c.egg-info/requires.txt
log2c.egg-info/top_level.txt