Metadata-Version: 1.0
Name: log2c
Version: 0.0.2
Summary: Crawling 2-channel threads in log
Home-page: UNKNOWN
Author: castaneai
Author-email: castaneai@castaneai.net
License: UNKNOWN
Platform: UNKNOWN
